flask_jwt_extended/__init__.py
flask_jwt_extended/config.py
flask_jwt_extended/default_callbacks.py
flask_jwt_extended/exceptions.py
flask_jwt_extended/internal_utils.py
flask_jwt_extended/jwt_manager.py
flask_jwt_extended/py.typed
flask_jwt_extended/tokens.py
flask_jwt_extended/typing.py
flask_jwt_extended/utils.py
flask_jwt_extended/view_decorators.py
Flask_JWT_Extended-4.7.0.dist-info/LICENSE
Flask_JWT_Extended-4.7.0.dist-info/METADATA
Flask_JWT_Extended-4.7.0.dist-info/WHEEL
Flask_JWT_Extended-4.7.0.dist-info/top_level.txt
Flask_JWT_Extended-4.7.0.dist-info/RECORD
