Metadata-Version: 2.1
Name: Flask-JWT-Extended
Version: 4.7.0
Summary: Extended JWT integration with Flask
Home-page: https://github.com/vimalloc/flask-jwt-extended
Author: Lily Acadia Gilbert
Author-email: lily.gilbert@hey.com
License: MIT
Keywords: flask,jwt,json web token
Platform: any
Classifier: Development Status :: 5 - Production/Stable
Classifier: Environment :: Web Environment
Classifier: Framework :: Flask
Classifier: Intended Audience :: Developers
Classifier: License :: OSI Approved :: MIT License
Classifier: Operating System :: OS Independent
Classifier: Programming Language :: Python
Classifier: Programming Language :: Python :: 3
Classifier: Programming Language :: Python :: 3 :: Only
Classifier: Programming Language :: Python :: 3.6
Classifier: Programming Language :: Python :: 3.7
Classifier: Programming Language :: Python :: 3.8
Classifier: Programming Language :: Python :: 3.9
Classifier: Programming Language :: Python :: 3.10
Classifier: Programming Language :: Python :: 3.11
Classifier: Programming Language :: Python :: 3.12
Classifier: Programming Language :: Python :: Implementation :: CPython
Classifier: Programming Language :: Python :: Implementation :: PyPy
Classifier: Topic :: Software Development :: Libraries :: Python Modules
Requires-Python: >=3.9,<4
License-File: LICENSE
Requires-Dist: Werkzeug>=0.14
Requires-Dist: Flask<4.0,>=2.0
Requires-Dist: PyJWT<3.0,>=2.0
Provides-Extra: asymmetric-crypto
Requires-Dist: cryptography>=3.3.1; extra == "asymmetric-crypto"
